{"settings":{"is24Hour":true,"roundingSeconds":15,"darkMode":false,"categories":[{"name":"Push","color":4294916912},{"name":"Pull","color":4289724909},{"name":"Travel Gym","color":4278255360}]},"legacyNotes":[{"timestamp":1720000000000,"title":"Schema 8 Push Day","text":"Bench Press 100 kg x5\n    Incline DB 80 lb x8\nCable Fly 30 kg x12","categoryName":"Push","categoryColor":4294916912,"learnings":"Keep elbows tucked."},{"timestamp":1720086400000,"title":"Schema 8 Pull Day","text":"Lat Pulldown 70 kg x10","categoryName":"Pull","categoryColor":4289724909,"learnings":"Grip felt stable."}],"legacyExercises":[{"exerciseId":201,"name":"Bench Press","parentId":null,"muscleGroup":"Chest","aliases":"bench,bp"},{"exerciseId":202,"name":"Lat Pulldown","parentId":null,"muscleGroup":"Back","aliases":"lat,lat pull"}],"legacySets":[{"setId":301,"workoutId":1720000000000,"exerciseId":201,"weight":100.0,"reps":5,"isUnilateral":false,"modifier":"top set","brand":null,"relativeTime":"00:05:00","absoluteTime":"18:35"},{"setId":302,"workoutId":1720000000000,"exerciseId":201,"weight":90.0,"reps":8,"isUnilateral":false,"modifier":"backoff","brand":null,"relativeTime":"00:08:00","absoluteTime":"18:38"},{"setId":303,"workoutId":1720086400000,"exerciseId":202,"weight":70.0,"reps":10,"isUnilateral":false,"modifier":null,"brand":"Technogym","relativeTime":"00:04:00","absoluteTime":"19:04"}],"canonicalCategories":[{"id":"cat-push","name":"Push","colorArgb":4294916912,"position":0,"isBuiltIn":true,"isArchived":false},{"id":"cat-pull","name":"Pull","colorArgb":4289724909,"position":1,"isBuiltIn":true,"isArchived":false}],"canonicalExercises":[{"id":"ex-bench","canonicalName":"Bench Press","normalizedName":"bench press","parentExerciseId":null,"muscleGroup":"Chest","createdAt":1720000000000,"updatedAt":1720000000000},{"id":"ex-incline-bench","canonicalName":"Incline Dumbbell Bench Press","normalizedName":"incline dumbbell bench press","parentExerciseId":"ex-bench","muscleGroup":"Chest","createdAt":1719999900000,"updatedAt":1720000000000},{"id":"ex-lat-pulldown","canonicalName":"Lat Pulldown","normalizedName":"lat pulldown","parentExerciseId":null,"muscleGroup":"Back","createdAt":1720086400000,"updatedAt":1720086400000}],"canonicalExerciseAliases":[{"id":"alias-bp","exerciseId":"ex-bench","normalizedAlias":"bp","originalAlias":"BP"},{"id":"alias-incline-db","exerciseId":"ex-incline-bench","normalizedAlias":"incline db","originalAlias":"Incline DB"},{"id":"alias-lat","exerciseId":"ex-lat-pulldown","normalizedAlias":"lat","originalAlias":"Lat"}],"canonicalWorkouts":[{"id":"workout-schema8-push","legacyTimestamp":1720000000000,"startedAt":1720000000000,"endedAt":1720005400000,"categoryId":"cat-push","title":"Schema 8 Push Day","learnings":"Keep elbows tucked.","status":"COMPLETED","rawDraftText":"Bench Press 100 kg x5\n    Incline DB 80 lb x8\nCable Fly 30 kg x12","legacyMigrationStatus":"IMPORTED","legacyMigrationMessage":"Fixture from schema 8 backup","createdAt":1720000000000,"updatedAt":1720005400000},{"id":"workout-schema8-pull","legacyTimestamp":1720086400000,"startedAt":1720086400000,"endedAt":1720090000000,"categoryId":"cat-pull","title":"Schema 8 Pull Day","learnings":"Grip felt stable.","status":"COMPLETED","rawDraftText":"Lat Pulldown 70 kg x10","legacyMigrationStatus":"IMPORTED","legacyMigrationMessage":"Fixture from schema 8 backup","createdAt":1720086400000,"updatedAt":1720090000000}],"canonicalWorkoutExercises":[{"id":"wex-push-bench","workoutId":"workout-schema8-push","exerciseId":"ex-bench","position":0,"mode":"BILATERAL","modifier":"top set","equipmentBrand":null,"startedAtOffsetSeconds":300,"startedAt":1720000300000,"legacyRelativeTimeText":"00:05:00","legacyAbsoluteTimeText":"18:35"},{"id":"wex-push-incline","workoutId":"workout-schema8-push","exerciseId":"ex-incline-bench","position":1,"mode":"UNILATERAL","modifier":"travel gym dumbbells","equipmentBrand":"Unknown hotel rack","startedAtOffsetSeconds":900,"startedAt":1720000900000,"legacyRelativeTimeText":"00:15:00","legacyAbsoluteTimeText":"18:45"},{"id":"wex-pull-lat","workoutId":"workout-schema8-pull","exerciseId":"ex-lat-pulldown","position":0,"mode":"BILATERAL","modifier":null,"equipmentBrand":"Technogym","startedAtOffsetSeconds":240,"startedAt":1720086640000,"legacyRelativeTimeText":"00:04:00","legacyAbsoluteTimeText":"19:04"}],"canonicalWorkoutSets":[{"id":"cset-bench-1","workoutExerciseId":"wex-push-bench","position":0,"repetitions":5,"weight":100.0,"weightUnit":"KG","durationSeconds":null,"distanceMeters":null,"performedAtOffsetSeconds":330,"rpe":8.5,"rir":1.5},{"id":"cset-bench-2","workoutExerciseId":"wex-push-bench","position":1,"repetitions":8,"weight":90.0,"weightUnit":"KG","durationSeconds":null,"distanceMeters":null,"performedAtOffsetSeconds":480,"rpe":8.0,"rir":2.0},{"id":"cset-incline-1","workoutExerciseId":"wex-push-incline","position":0,"repetitions":8,"weight":80.0,"weightUnit":"LB","durationSeconds":null,"distanceMeters":null,"performedAtOffsetSeconds":930,"rpe":7.5,"rir":2.5},{"id":"cset-lat-1","workoutExerciseId":"wex-pull-lat","position":0,"repetitions":10,"weight":70.0,"weightUnit":"KG","durationSeconds":null,"distanceMeters":null,"performedAtOffsetSeconds":260,"rpe":8.0,"rir":2.0}]}